{
  "m_GameObject": {
    "m_FileID": 0,
    "m_PathID": 0
  },
  "m_Enabled": 1,
  "m_Script": {
    "m_FileID": 0,
    "m_PathID": 9218491004411354591
  },
  "m_Name": "AudiTTRSTurbo2",
  "animationCurve": {
    "m_Curve": [
      {
        "time": 1000.0,
        "value": 0.320707917,
        "inSlope": 3.54899421E-05,
        "outSlope": 3.54899421E-05,
        "weightedMode": 0,
        "inWeight": 0.333333343,
        "outWeight": 0.333333343
      },
      {
        "time": 2250.0,
        "value": 0.365070343,
        "inSlope": 3.54899421E-05,
        "outSlope": 1.20117128,
        "weightedMode": 0,
        "inWeight": 0.333333343,
        "outWeight": 0.333333343
      },
      {
        "time": 2252.25,
        "value": 3.06770563,
        "inSlope": 1.20117128,
        "outSlope": 0.005121999,
        "weightedMode": 0,
        "inWeight": 0.333333343,
        "outWeight": 0.333333343
      },
      {
        "time": 2900.0,
        "value": 6.3854804,
        "inSlope": 0.005121999,
        "outSlope": 0.00114244223,
        "weightedMode": 0,
        "inWeight": 0.333333343,
        "outWeight": 0.333333343
      },
      {
        "time": 3900.0,
        "value": 7.52792263,
        "inSlope": 0.00114244223,
        "outSlope": 0.000276981358,
        "weightedMode": 0,
        "inWeight": 0.333333343,
        "outWeight": 0.333333343
      },
      {
        "time": 4400.0,
        "value": 7.66641331,
        "inSlope": 0.000276981358,
        "outSlope": -0.000460675568,
        "weightedMode": 0,
        "inWeight": 0.333333343,
        "outWeight": 0.333333343
      },
      {
        "time": 5450.0,
        "value": 7.182704,
        "inSlope": -0.000460675568,
        "outSlope": -0.00207766518,
        "weightedMode": 0,
        "inWeight": 0.333333343,
        "outWeight": 0.333333343
      },
      {
        "time": 7000.0,
        "value": 3.962323,
        "inSlope": -0.00207766518,
        "outSlope": -0.00181732781,
        "weightedMode": 0,
        "inWeight": 0.333333343,
        "outWeight": 0.333333343
      }
    ],
    "m_PreInfinity": 2,
    "m_PostInfinity": 2,
    "m_RotationOrder": 4
  }
}