{
  "m_GameObject": {
    "m_FileID": 0,
    "m_PathID": 0
  },
  "m_Enabled": 1,
  "m_Script": {
    "m_FileID": 0,
    "m_PathID": 9218491004411354591
  },
  "m_Name": "California30Intake5",
  "animationCurve": {
    "m_Curve": [
      {
        "time": 1000.0,
        "value": 4.4488893,
        "inSlope": 0.00050202804,
        "outSlope": 0.0005188922,
        "weightedMode": 0,
        "inWeight": 0.33333334,
        "outWeight": 0.33333334
      },
      {
        "time": 2200.0,
        "value": 5.07156,
        "inSlope": 0.0005188922,
        "outSlope": 0.0001962125,
        "weightedMode": 0,
        "inWeight": 0.33333334,
        "outWeight": 0.33333334
      },
      {
        "time": 3950.0,
        "value": 5.414932,
        "inSlope": 0.0001962125,
        "outSlope": -2.1936678E-05,
        "weightedMode": 0,
        "inWeight": 0.33333334,
        "outWeight": 0.33333334
      },
      {
        "time": 5050.0,
        "value": 5.3908014,
        "inSlope": -2.1936678E-05,
        "outSlope": -4.3438453E-05,
        "weightedMode": 0,
        "inWeight": 0.33333334,
        "outWeight": 0.33333334
      },
      {
        "time": 6400.0,
        "value": 5.3321595,
        "inSlope": -4.3438453E-05,
        "outSlope": -0.0025446527,
        "weightedMode": 0,
        "inWeight": 0.33333334,
        "outWeight": 0.33333334
      }
    ],
    "m_PreInfinity": 2,
    "m_PostInfinity": 2,
    "m_RotationOrder": 4
  }
}