{
  "m_GameObject": {
    "m_FileID": 0,
    "m_PathID": 0
  },
  "m_Enabled": 1,
  "m_Script": {
    "m_FileID": 0,
    "m_PathID": 9218491004411354591
  },
  "m_Name": "Dodge_HavocChallenger_1970Turbo4",
  "animationCurve": {
    "m_Curve": [
      {
        "time": 1000.0,
        "value": 1.97698176,
        "inSlope": 4.46522245E-06,
        "outSlope": 0.000401083118,
        "weightedMode": 0,
        "inWeight": 0.333333343,
        "outWeight": 0.333333343
      },
      {
        "time": 1999.99817,
        "value": 2.37806416,
        "inSlope": 0.000401083118,
        "outSlope": 3.69148374,
        "weightedMode": 0,
        "inWeight": 0.333333343,
        "outWeight": 0.333333343
      },
      {
        "time": 2001.99829,
        "value": 9.761482,
        "inSlope": 3.69148374,
        "outSlope": 0.00185782032,
        "weightedMode": 0,
        "inWeight": 0.333333343,
        "outWeight": 0.333333343
      },
      {
        "time": 2650.0,
        "value": 10.965353,
        "inSlope": 0.00185782032,
        "outSlope": 0.00133192178,
        "weightedMode": 0,
        "inWeight": 0.333333343,
        "outWeight": 0.333333343
      },
      {
        "time": 3500.0,
        "value": 12.0974865,
        "inSlope": 0.00133192178,
        "outSlope": -0.000567255,
        "weightedMode": 0,
        "inWeight": 0.333333343,
        "outWeight": 0.333333343
      },
      {
        "time": 5500.0,
        "value": 10.9629765,
        "inSlope": -0.000567255,
        "outSlope": -0.0010747161,
        "weightedMode": 0,
        "inWeight": 0.333333343,
        "outWeight": 0.333333343
      },
      {
        "time": 7202.15674,
        "value": 9.133641,
        "inSlope": -0.0010747161,
        "outSlope": 0.0,
        "weightedMode": 0,
        "inWeight": 0.333333343,
        "outWeight": 0.333333343
      }
    ],
    "m_PreInfinity": 2,
    "m_PostInfinity": 2,
    "m_RotationOrder": 4
  }
}