{
  "m_GameObject": {
    "m_FileID": 0,
    "m_PathID": 0
  },
  "m_Enabled": 1,
  "m_Script": {
    "m_FileID": 0,
    "m_PathID": 9218491004411354591
  },
  "m_Name": "F4WRXEngine4",
  "animationCurve": {
    "m_Curve": [
      {
        "time": 1000.0,
        "value": 4.82631254,
        "inSlope": 0.0120272031,
        "outSlope": 0.0120272031,
        "weightedMode": 0,
        "inWeight": 0.333333343,
        "outWeight": 0.333333343
      },
      {
        "time": 1150.0,
        "value": 6.630393,
        "inSlope": 0.0120272031,
        "outSlope": 0.004533646,
        "weightedMode": 0,
        "inWeight": 0.333333343,
        "outWeight": 0.333333343
      },
      {
        "time": 1350.0,
        "value": 7.53712225,
        "inSlope": 0.004533646,
        "outSlope": 0.000314209115,
        "weightedMode": 0,
        "inWeight": 0.333333343,
        "outWeight": 0.333333343
      },
      {
        "time": 2050.0,
        "value": 7.75706863,
        "inSlope": 0.000314209115,
        "outSlope": -8.50893339E-05,
        "weightedMode": 0,
        "inWeight": 0.333333343,
        "outWeight": 0.333333343
      },
      {
        "time": 3000.0,
        "value": 7.676234,
        "inSlope": -8.50893339E-05,
        "outSlope": -0.000225286043,
        "weightedMode": 0,
        "inWeight": 0.333333343,
        "outWeight": 0.333333343
      },
      {
        "time": 4100.0,
        "value": 7.428419,
        "inSlope": -0.000225286043,
        "outSlope": -0.000620378938,
        "weightedMode": 0,
        "inWeight": 0.333333343,
        "outWeight": 0.333333343
      },
      {
        "time": 5550.0,
        "value": 6.52886963,
        "inSlope": -0.000620378938,
        "outSlope": -0.00034328067,
        "weightedMode": 0,
        "inWeight": 0.333333343,
        "outWeight": 0.333333343
      }
    ],
    "m_PreInfinity": 2,
    "m_PostInfinity": 2,
    "m_RotationOrder": 4
  }
}