{
  "m_GameObject": {
    "m_FileID": 0,
    "m_PathID": 0
  },
  "m_Enabled": 1,
  "m_Script": {
    "m_FileID": 0,
    "m_PathID": 9218491004411354591
  },
  "m_Name": "Ginetta_Akula_2019BaseTorqueCurve",
  "animationCurve": {
    "m_Curve": [
      {
        "time": 1000.0,
        "value": 131.947052,
        "inSlope": -0.000374196359,
        "outSlope": -0.000374196359,
        "weightedMode": 0,
        "inWeight": 0.333333343,
        "outWeight": 0.333333343
      },
      {
        "time": 1398.6,
        "value": 131.7979,
        "inSlope": -0.000374196359,
        "outSlope": 0.00112927181,
        "weightedMode": 0,
        "inWeight": 0.333333343,
        "outWeight": 0.333333343
      },
      {
        "time": 1700.0,
        "value": 132.13826,
        "inSlope": 0.00112927181,
        "outSlope": 0.290564328,
        "weightedMode": 0,
        "inWeight": 0.333333343,
        "outWeight": 0.333333343
      },
      {
        "time": 2447.55,
        "value": 349.34964,
        "inSlope": 0.290564328,
        "outSlope": 64.5624847,
        "weightedMode": 0,
        "inWeight": 0.333333343,
        "outWeight": 0.333333343
      },
      {
        "time": 2450.0,
        "value": 507.524567,
        "inSlope": 64.5624847,
        "outSlope": 0.0618731268,
        "weightedMode": 0,
        "inWeight": 0.333333343,
        "outWeight": 0.333333343
      },
      {
        "time": 3150.0,
        "value": 550.835754,
        "inSlope": 0.0618731268,
        "outSlope": 0.0530315675,
        "weightedMode": 0,
        "inWeight": 0.333333343,
        "outWeight": 0.333333343
      },
      {
        "time": 3800.0,
        "value": 585.3063,
        "inSlope": 0.0530315675,
        "outSlope": 0.05379476,
        "weightedMode": 0,
        "inWeight": 0.333333343,
        "outWeight": 0.333333343
      },
      {
        "time": 4400.0,
        "value": 617.5831,
        "inSlope": 0.05379476,
        "outSlope": 0.0102941077,
        "weightedMode": 0,
        "inWeight": 0.333333343,
        "outWeight": 0.333333343
      },
      {
        "time": 5150.0,
        "value": 625.3037,
        "inSlope": 0.0102941077,
        "outSlope": -0.0501496457,
        "weightedMode": 0,
        "inWeight": 0.333333343,
        "outWeight": 0.333333343
      },
      {
        "time": 6000.0,
        "value": 582.6765,
        "inSlope": -0.0501496457,
        "outSlope": -0.149614215,
        "weightedMode": 0,
        "inWeight": 0.333333343,
        "outWeight": 0.333333343
      },
      {
        "time": 6800.0,
        "value": 462.985138,
        "inSlope": -0.149614215,
        "outSlope": -0.332772225,
        "weightedMode": 0,
        "inWeight": 0.333333343,
        "outWeight": 0.333333343
      },
      {
        "time": 7050.0,
        "value": 379.792084,
        "inSlope": -0.332772225,
        "outSlope": -0.332772225,
        "weightedMode": 0,
        "inWeight": 0.333333343,
        "outWeight": 0.333333343
      }
    ],
    "m_PreInfinity": 2,
    "m_PostInfinity": 2,
    "m_RotationOrder": 4
  }
}