{
  "m_GameObject": {
    "m_FileID": 0,
    "m_PathID": 0
  },
  "m_Enabled": 1,
  "m_Script": {
    "m_FileID": 0,
    "m_PathID": 9218491004411354591
  },
  "m_Name": "GT40MKIIEngine5",
  "animationCurve": {
    "m_Curve": [
      {
        "time": 1050.0,
        "value": 1.5599437,
        "inSlope": 0.00050222897,
        "outSlope": 0.0023634108,
        "weightedMode": 0,
        "inWeight": 0.33333334,
        "outWeight": 0.33333334
      },
      {
        "time": 1600.0,
        "value": 2.8598197,
        "inSlope": 0.0023634108,
        "outSlope": 0.0025970766,
        "weightedMode": 0,
        "inWeight": 0.33333334,
        "outWeight": 0.33333334
      },
      {
        "time": 2200.0,
        "value": 4.4180655,
        "inSlope": 0.0025970766,
        "outSlope": 0.0020746184,
        "weightedMode": 0,
        "inWeight": 0.33333334,
        "outWeight": 0.33333334
      },
      {
        "time": 2600.0,
        "value": 5.247913,
        "inSlope": 0.0020746184,
        "outSlope": 0.0009982515,
        "weightedMode": 0,
        "inWeight": 0.33333334,
        "outWeight": 0.33333334
      },
      {
        "time": 3200.0,
        "value": 5.8468637,
        "inSlope": 0.0009982515,
        "outSlope": 0.0002454582,
        "weightedMode": 0,
        "inWeight": 0.33333334,
        "outWeight": 0.33333334
      },
      {
        "time": 4150.0,
        "value": 6.080049,
        "inSlope": 0.0002454582,
        "outSlope": -6.6045126E-05,
        "weightedMode": 0,
        "inWeight": 0.33333334,
        "outWeight": 0.33333334
      },
      {
        "time": 5050.0,
        "value": 6.0206084,
        "inSlope": -6.6045126E-05,
        "outSlope": -0.000846959,
        "weightedMode": 0,
        "inWeight": 0.33333334,
        "outWeight": 0.33333334
      },
      {
        "time": 6200.0,
        "value": 5.0466056,
        "inSlope": -0.000846959,
        "outSlope": -0.0008906987,
        "weightedMode": 0,
        "inWeight": 0.33333334,
        "outWeight": 0.33333334
      }
    ],
    "m_PreInfinity": 2,
    "m_PostInfinity": 2,
    "m_RotationOrder": 4
  }
}