{
  "m_GameObject": {
    "m_FileID": 0,
    "m_PathID": 0
  },
  "m_Enabled": 1,
  "m_Script": {
    "m_FileID": 0,
    "m_PathID": 7467269084997592608
  },
  "m_Name": "GTASpanoWheelSpin",
  "animationCurve": {
    "m_Curve": [
      {
        "time": 1045.41858,
        "value": 0.86960876,
        "inSlope": 2.33817282E-05,
        "outSlope": 1.87430142E-05,
        "weightedMode": 0,
        "inWeight": 0.333333343,
        "outWeight": 0.333333343
      },
      {
        "time": 5086.45654,
        "value": 0.94535,
        "inSlope": 1.87430142E-05,
        "outSlope": -0.00153015682,
        "weightedMode": 0,
        "inWeight": 0.333333343,
        "outWeight": 0.333333343
      },
      {
        "time": 5704.269,
        "value": 0.0,
        "inSlope": -0.00153015682,
        "outSlope": 0.0,
        "weightedMode": 0,
        "inWeight": 0.333333343,
        "outWeight": 0.333333343
      },
      {
        "time": 6253.486,
        "value": 0.0,
        "inSlope": 0.0,
        "outSlope": 0.000433532521,
        "weightedMode": 0,
        "inWeight": 0.333333343,
        "outWeight": 0.333333343
      },
      {
        "time": 8473.358,
        "value": 0.962386966,
        "inSlope": 0.000433532521,
        "outSlope": 0.000146317456,
        "weightedMode": 0,
        "inWeight": 0.333333343,
        "outWeight": 0.333333343
      },
      {
        "time": 9963.473,
        "value": 1.1804167,
        "inSlope": 0.000146317456,
        "outSlope": 7.626836E-05,
        "weightedMode": 0,
        "inWeight": 0.333333343,
        "outWeight": 0.333333343
      }
    ],
    "m_PreInfinity": 2,
    "m_PostInfinity": 2,
    "m_RotationOrder": 4
  }
}