{
  "m_GameObject": {
    "m_FileID": 0,
    "m_PathID": 0
  },
  "m_Enabled": 1,
  "m_Script": {
    "m_FileID": 0,
    "m_PathID": 9218491004411354591
  },
  "m_Name": "HuayraTurbo5",
  "animationCurve": {
    "m_Curve": [
      {
        "time": 1100.0,
        "value": 0.0,
        "inSlope": 0.00179633021,
        "outSlope": 0.0703276545,
        "weightedMode": 0,
        "inWeight": 0.333333343,
        "outWeight": 0.333333343
      },
      {
        "time": 1250.0,
        "value": 10.5491486,
        "inSlope": 0.0703276545,
        "outSlope": 0.0332419463,
        "weightedMode": 0,
        "inWeight": 0.333333343,
        "outWeight": 0.333333343
      },
      {
        "time": 1501.50012,
        "value": 18.909502,
        "inSlope": 0.0332419463,
        "outSlope": 0.0289104078,
        "weightedMode": 0,
        "inWeight": 0.333333343,
        "outWeight": 0.333333343
      },
      {
        "time": 1950.0,
        "value": 31.8758163,
        "inSlope": 0.0289104078,
        "outSlope": 0.01862045,
        "weightedMode": 0,
        "inWeight": 0.333333343,
        "outWeight": 0.333333343
      },
      {
        "time": 2352.35,
        "value": 39.3677559,
        "inSlope": 0.01862045,
        "outSlope": 0.0172402523,
        "weightedMode": 0,
        "inWeight": 0.333333343,
        "outWeight": 0.333333343
      },
      {
        "time": 3150.0,
        "value": 53.119442,
        "inSlope": 0.0172402523,
        "outSlope": 0.00237886747,
        "weightedMode": 0,
        "inWeight": 0.333333343,
        "outWeight": 0.333333343
      },
      {
        "time": 4350.0,
        "value": 55.9740829,
        "inSlope": 0.00237886747,
        "outSlope": -0.00169101986,
        "weightedMode": 0,
        "inWeight": 0.333333343,
        "outWeight": 0.333333343
      },
      {
        "time": 6500.0,
        "value": 52.33839,
        "inSlope": -0.00169101986,
        "outSlope": -0.000288379379,
        "weightedMode": 0,
        "inWeight": 0.333333343,
        "outWeight": 0.333333343
      }
    ],
    "m_PreInfinity": 2,
    "m_PostInfinity": 2,
    "m_RotationOrder": 4
  }
}