{
  "m_GameObject": {
    "m_FileID": 0,
    "m_PathID": 0
  },
  "m_Enabled": 1,
  "m_Script": {
    "m_FileID": 0,
    "m_PathID": 9218491004411354591
  },
  "m_Name": "Nissan_StillenMaximaF1_1999BaseTorqueCurve",
  "animationCurve": {
    "m_Curve": [
      {
        "time": 1000.0,
        "value": 200.822754,
        "inSlope": 0.0032411702,
        "outSlope": 0.0032411702,
        "weightedMode": 0,
        "inWeight": 0.333333343,
        "outWeight": 0.333333343
      },
      {
        "time": 1300.0,
        "value": 201.7951,
        "inSlope": 0.0032411702,
        "outSlope": 0.0009773636,
        "weightedMode": 0,
        "inWeight": 0.333333343,
        "outWeight": 0.333333343
      },
      {
        "time": 1700.0,
        "value": 202.18605,
        "inSlope": 0.0009773636,
        "outSlope": 0.328447372,
        "weightedMode": 0,
        "inWeight": 0.333333343,
        "outWeight": 0.333333343
      },
      {
        "time": 2350.0,
        "value": 415.676849,
        "inSlope": 0.328447372,
        "outSlope": 0.0456635132,
        "weightedMode": 0,
        "inWeight": 0.333333343,
        "outWeight": 0.333333343
      },
      {
        "time": 2850.0,
        "value": 438.5086,
        "inSlope": 0.0456635132,
        "outSlope": 0.0288062133,
        "weightedMode": 0,
        "inWeight": 0.333333343,
        "outWeight": 0.333333343
      },
      {
        "time": 3350.0,
        "value": 452.9117,
        "inSlope": 0.0288062133,
        "outSlope": 0.007550727,
        "weightedMode": 0,
        "inWeight": 0.333333343,
        "outWeight": 0.333333343
      },
      {
        "time": 4250.0,
        "value": 459.707367,
        "inSlope": 0.007550727,
        "outSlope": -0.0020223388,
        "weightedMode": 0,
        "inWeight": 0.333333343,
        "outWeight": 0.333333343
      },
      {
        "time": 5000.0,
        "value": 458.1906,
        "inSlope": -0.0020223388,
        "outSlope": -0.00503018452,
        "weightedMode": 0,
        "inWeight": 0.333333343,
        "outWeight": 0.333333343
      },
      {
        "time": 5550.0,
        "value": 455.424,
        "inSlope": -0.00503018452,
        "outSlope": -0.1687561,
        "weightedMode": 0,
        "inWeight": 0.333333343,
        "outWeight": 0.333333343
      },
      {
        "time": 6000.0,
        "value": 379.483765,
        "inSlope": -0.1687561,
        "outSlope": -0.164274976,
        "weightedMode": 0,
        "inWeight": 0.333333343,
        "outWeight": 0.333333343
      },
      {
        "time": 6450.0,
        "value": 305.560028,
        "inSlope": -0.164274976,
        "outSlope": -0.06404463,
        "weightedMode": 0,
        "inWeight": 0.333333343,
        "outWeight": 0.333333343
      },
      {
        "time": 7000.0,
        "value": 270.33548,
        "inSlope": -0.06404463,
        "outSlope": -0.04084782,
        "weightedMode": 0,
        "inWeight": 0.333333343,
        "outWeight": 0.333333343
      }
    ],
    "m_PreInfinity": 2,
    "m_PostInfinity": 2,
    "m_RotationOrder": 4
  }
}