{
  "m_GameObject": {
    "m_FileID": 0,
    "m_PathID": 0
  },
  "m_Enabled": 1,
  "m_Script": {
    "m_FileID": 0,
    "m_PathID": 9218491004411354591
  },
  "m_Name": "VeyronWREBaseTorqueCurve",
  "animationCurve": {
    "m_Curve": [
      {
        "time": 1000.0,
        "value": 243.233734,
        "inSlope": 0.459210157,
        "outSlope": -0.000198745722,
        "weightedMode": 0,
        "inWeight": 0.333333343,
        "outWeight": 0.333333343
      },
      {
        "time": 1200.0,
        "value": 243.193985,
        "inSlope": -0.000198745722,
        "outSlope": 0.00398010248,
        "weightedMode": 0,
        "inWeight": 0.333333343,
        "outWeight": 0.333333343
      },
      {
        "time": 1400.0,
        "value": 243.99,
        "inSlope": 0.00398010248,
        "outSlope": 1.150896,
        "weightedMode": 0,
        "inWeight": 0.333333343,
        "outWeight": 0.333333343
      },
      {
        "time": 1650.0,
        "value": 531.714,
        "inSlope": 1.150896,
        "outSlope": 0.426975459,
        "weightedMode": 0,
        "inWeight": 0.333333343,
        "outWeight": 0.333333343
      },
      {
        "time": 3000.0,
        "value": 1108.13086,
        "inSlope": 0.426975459,
        "outSlope": 0.0155939944,
        "weightedMode": 0,
        "inWeight": 0.333333343,
        "outWeight": 0.333333343
      },
      {
        "time": 3500.0,
        "value": 1115.92786,
        "inSlope": 0.0155939944,
        "outSlope": 0.0,
        "weightedMode": 0,
        "inWeight": 0.333333343,
        "outWeight": 0.333333343
      },
      {
        "time": 4139.748,
        "value": 1115.92786,
        "inSlope": 0.0,
        "outSlope": 0.008228229,
        "weightedMode": 0,
        "inWeight": 0.333333343,
        "outWeight": 0.333333343
      },
      {
        "time": 4650.892,
        "value": 1120.13367,
        "inSlope": 0.008228229,
        "outSlope": 0.0134994294,
        "weightedMode": 0,
        "inWeight": 0.333333343,
        "outWeight": 0.333333343
      },
      {
        "time": 5118.224,
        "value": 1126.44238,
        "inSlope": 0.0134994294,
        "outSlope": -0.121734761,
        "weightedMode": 0,
        "inWeight": 0.333333343,
        "outWeight": 0.333333343
      },
      {
        "time": 6400.0,
        "value": 970.4057,
        "inSlope": -0.121734761,
        "outSlope": -0.118752114,
        "weightedMode": 0,
        "inWeight": 0.333333343,
        "outWeight": 0.333333343
      }
    ],
    "m_PreInfinity": 2,
    "m_PostInfinity": 2,
    "m_RotationOrder": 4
  }
}